scia_xml_reader/__init__.py
scia_xml_reader/config.py
scia_xml_reader/exceptions.py
scia_xml_reader/functions.py
scia_xml_reader/getters.py
scia_xml_reader/mapping.py
scia_xml_reader/models.py
scia_xml_reader/parse_info.py
scia_xml_reader/parser.py
scia_xml_reader-0.1.0.dist-info/METADATA
scia_xml_reader-0.1.0.dist-info/WHEEL
scia_xml_reader-0.1.0.dist-info/RECORD
