Metadata-Version: 2.1
Name: scia-xml-reader
Version: 0.1.0
Summary: 
Author: Marijn Drillenburg
Author-email: m.drillenburg@gmail.com
Requires-Python: >=3.11,<4.0
Classifier: Programming Language :: Python :: 3
Classifier: Programming Language :: Python :: 3.11
Requires-Dist: pydantic (>=2.7.1,<3.0.0)
